Workbook

Sheet DCF Model
B2: Tata Consultancy Services — Discounted Cash Flow Model
B3: INR crore unless stated · Consolidated · Valuation date 31-Mar-2026 (FY26 end) · Cross-checked against the Python DCF
B5: Italic blue blocks explain each stage; the green Notes column (far right) gives a plain-language reason for every line. Discounting uses simple 1/(1+WACC)^t arithmetic.
B6: Colours: blue = number you enter · black = calculated · yellow = check or update before relying on it
B8: STAGE 1 — Assumptions (the numbers you enter) | K8: NOTES — plain-language reasons
B9: These are the numbers you type in; everything else in the model is calculated from them. WACC and the two growth rates have the biggest effect on the final value, so they sit at the top. Cash and debt are here too, but they don't affect the yearly cash flows — they're used only at the very end, to turn the value of the business into the value for shareholders. Yellow cells are the ones to double-check or update before you rely on the model.
B15: Tax Rate | D15: 0.24 | K15: TCS paid about 24% of its profit in tax in FY26. We use the after-tax amount because a company only keeps what's left after tax, and that is what investors can actually claim.
B16: Discount Rate (WACC) | D16: =D142 -> 0.12689574 | K16: The yearly return TCS's investors expect, and the rate used to bring future cash back to today's value. It isn't typed in — it is worked out in Stage 6 and copied here.
B17: Terminal Growth (g) | D17: 0.05 | K17: The rate at which we assume cash flows keep growing forever, after the 5-year forecast. It must be smaller than WACC, or the terminal-value formula gives a meaningless (negative or infinite) answer.
B18: Explicit Growth | D18: 0.06 | K18: How fast cash flows grow during the 5 forecast years. 6% is based on TCS's recent revenue and profit growth, not a guess.
B19: Exit EV/EBITDA (x) | D19: 12 | K19: Used only as a second opinion on the terminal value: what a buyer might pay, as a multiple of one year's EBITDA. TCS trades at about 12 times EBITDA today, so we use 12.
B20: Valuation date (FY-end) | D20: 46112 | K20: The date we value the company as of. Everything is discounted back to here; the five forecast years are the March year-ends after it.
B21: Current Price (INR) | D21: 2465 | K21: Today's market price — the only figure we take from the market rather than estimate. We judge our own estimate against it. It changes daily, so update it before sharing the model.
B22: Shares Outstanding (cr) | D22: 361.81 | K22: The number of TCS shares (about 361.8 crore). We divide total equity value by this to get the value of one share.
B23: Debt (INR cr) | D23: 11283 | K23: What TCS owes — for TCS this is only lease obligations, as it has almost no borrowing. We subtract it when going from business value to shareholder value.
B24: Cash & Investments (INR cr) | D24: 50020 | K24: Cash plus investments TCS holds. Shareholders own this on top of the business, so we add it back at the end. It must include investments, where TCS keeps a large amount.
B25: Capex (INR cr) | D25: 4146 | K25: Money TCS spends each year on equipment and offices. It is real cash leaving the company, so we subtract it when working out free cash flow.
B27: Quick checks (calculated automatically)
B28: Net Cash (Cash & Inv − Debt) | D28: =D24-D23 -> 38737 | K28: Cash and investments minus debt = ₹38,737 cr. This is added when moving from business value to shareholder value. (Python's ₹55,000 was too high — more than the cash the company actually holds.)
B29: Implied Market Cap (Price × Shares) | D29: =D21*D22 -> 891861.65 | K29: Share price times number of shares = what the market currently values all of TCS's shares at.
B30: Implied Current EV (MktCap − Net Cash) | D30: =D29-D28 -> 853124.65 | K30: Market cap minus net cash = what the market thinks TCS's core business is worth. We compare our own business-value estimate against this.
B33: STAGE 2 — Unlevered Free Cash Flow (the cash the business makes) | K33: NOTES — plain-language reasons
B34: This works out the cash the business actually generates each year, available to everyone who funds it (lenders and shareholders) — which is why it is called 'unlevered', meaning before the effect of borrowing. We start from EBIT (operating profit, before interest and tax), not net profit, because net profit is already after interest and we don't want financing mixed in yet. From EBIT we take off tax, add back depreciation (not a real cash outflow), take off money spent on assets, and take off the extra cash tied up as the business grows. FY26 is the latest actual year; FY27 to FY31 grow from it at the chosen rate.
B40: Line item (FY26A = starting point) | D40: FY26A | E40: FY27F | F40: FY28F | G40: FY29F | H40: FY30F | I40: FY31F
B41: EBIT | D41: 66838 | E41: =D41*(1+$D$18) -> 70848.28 | F41: =E41*(1+$D$18) -> 75099.177 | G41: =F41*(1+$D$18) -> 79605.127 | H41: =G41*(1+$D$18) -> 84381.435 | I41: =H41*(1+$D$18) -> 89444.321 | K41: Operating profit before interest and tax. We get it from EBITDA (72,398) minus depreciation (5,560) = 66,838. Note: Screener calls EBITDA 'Operating Profit', so if you forget to subtract depreciation you overstate profit.
B42: Less: Cash Taxes | D42: =D41*$D$15 -> 16041.12 | E42: =E41*$D$15 -> 17003.587 | F42: =F41*$D$15 -> 18023.802 | G42: =G41*$D$15 -> 19105.231 | H42: =H41*$D$15 -> 20251.544 | I42: =I41*$D$15 -> 21466.637 | K42: Tax charged on that operating profit. We apply tax to EBIT itself, not to after-interest profit, so the result stays before-financing. The tax saved by using debt is dealt with inside WACC instead, so it isn't counted twice.
B43: Plus: D&A | D43: 5560 | E43: =D43*(1+$D$18) -> 5893.6 | F43: =E43*(1+$D$18) -> 6247.216 | G43: =F43*(1+$D$18) -> 6622.049 | H43: =G43*(1+$D$18) -> 7019.3719 | I43: =H43*(1+$D$18) -> 7440.5342 | K43: Depreciation was subtracted to reach EBIT, but it is not money leaving the company — it just spreads past spending over time in the accounts. Since we only want real cash, we add it back.
B44: Less: Capex | D44: =$D$25 -> 4146 | E44: =D44*(1+$D$18) -> 4394.76 | F44: =E44*(1+$D$18) -> 4658.4456 | G44: =F44*(1+$D$18) -> 4937.9523 | H44: =G44*(1+$D$18) -> 5234.2295 | I44: =H44*(1+$D$18) -> 5548.2832 | K44: Cash spent on new assets this year. The accounts spread this cost over several years as depreciation, but the cash goes out now, so a cash model subtracts the whole amount here.
B45: Less: Changes in NWC | D45: 2210 | E45: =D45*(1+$D$18) -> 2342.6 | F45: =E45*(1+$D$18) -> 2483.156 | G45: =F45*(1+$D$18) -> 2632.1454 | H45: =G45*(1+$D$18) -> 2790.0741 | I45: =H45*(1+$D$18) -> 2957.4785 | K45: As the business grows it ties up cash in unpaid customer bills and stock before it comes back. Watch the sign: the cash-flow statement showed this as −2,210 (cash used). This row is 'Less' and gets subtracted, so we enter +2,210 to get the same effect.
B46: Unlevered FCF | D46: =D41-D42+D43-D44-D45 -> 50000.88 | E46: =E41-E42+E43-E44-E45 -> 53000.933 | F46: =F41-F42+F43-F44-F45 -> 56180.989 | G46: =G41-G42+G43-G44-G45 -> 59551.848 | H46: =H41-H42+H43-H44-H45 -> 63124.959 | I46: =I41-I42+I43-I44-I45 -> 66912.457 | K46: What's left is the cash the whole business makes in a year, free for all investors. FY26 comes to 50,001 — the same number the Python model gave, so the two agree before any discounting.
B48: FY26 is the starting point (not discounted). Each later year = previous year × (1 + explicit growth, D18).
B51: STAGE 3 — Discounting the forecast to today's value | K51: NOTES — plain-language reasons
B52: Money in the future is worth less than money today, so each forecast year's cash flow is scaled down to its value today before we add them up. The scaling factor is 1 divided by (1+WACC) raised to the year number — the same simple method as the Python model (this replaces the earlier XNPV function). Multiply each year's cash flow by its factor, then add the five together to get the value of the forecast period in today's money. The terminal value — usually the larger part — is handled next.
B58: Discounting steps | E58: FY27F | F58: FY28F | G58: FY29F | H58: FY30F | I58: FY31F
B59: Time period t (yrs) | E59: 1 | F59: =E59+1 -> 2 | G59: =F59+1 -> 3 | H59: =G59+1 -> 4 | I59: =H59+1 -> 5 | K59: How many years ahead each cash flow is: year 1 is FY27, up to year 5 in FY31.
B60: Discount factor 1/(1+WACC)^t | E60: =1/(1+$D$16)^E59 -> 0.88739354 | F60: =1/(1+$D$16)^F59 -> 0.78746729 | G60: =1/(1+$D$16)^G59 -> 0.69879338 | H60: =1/(1+$D$16)^H59 -> 0.62010473 | I60: =1/(1+$D$16)^I59 -> 0.55027693 | K60: How much ₹1 in that future year is worth today, found with 1 ÷ (1+WACC) raised to the year number. It shrinks each year, because money in hand now is worth more than the same money later.
B61: Unlevered FCF (from Stage 2) | E61: =E46 -> 53000.933 | F61: =F46 -> 56180.989 | G61: =G46 -> 59551.848 | H61: =H46 -> 63124.959 | I61: =I46 -> 66912.457 | K61: The free cash flow figures copied down from Stage 2.
B62: PV of FCF (= FCF × factor) | E62: =E61*E60 -> 47032.685 | F62: =F61*F60 -> 44240.691 | G62: =G61*G60 -> 41614.437 | H62: =H61*H60 -> 39144.086 | I62: =I61*I60 -> 36820.381 | K62: Each year's cash flow multiplied by its discount factor — its worth in today's money.
B64: PV of explicit FCFs (add the 5) | D64: =SUM(E62:I62) -> 208852.28 | K64: Simply add the five discounted cash flows together. Plain addition — no special function.
B67: STAGE 4 — Terminal value (the worth of everything after FY31) | K67: NOTES — plain-language reasons
B68: The forecast only runs to FY31, but the company keeps going, so we estimate the value of everything after FY31 as one number and bring it back to today. We do it two ways as a check. The Gordon method assumes cash flows keep growing at a steady rate forever. The exit-multiple method assumes a buyer pays a set multiple of the final year's EBITDA. Because the terminal value is usually the largest part of the total, its assumptions deserve the most care.
B75: Last-year Unlevered FCF (FY31) | D75: =I46 -> 66912.457 | K75: The free cash flow in the final forecast year. The forever-growing value is built from this.
B76: Gordon TV = FCF×(1+g)/(WACC−g) | D76: =I46*(1+$D$17)/($D$16-$D$17) -> 913679.68 | K76: The value, at the end of FY31, of every cash flow from FY32 onwards, assuming they grow at g forever: last cash flow × (1+g), divided by (WACC − g).
B77: Last-year EBITDA (EBIT + D&A) | D77: =I41+I43 -> 96884.855 | K77: Final-year EBIT plus depreciation. This is the figure the exit multiple is applied to.
B78: Exit-multiple TV = EV/EBITDA × EBITDA | D78: =$D$19*D77 -> 1162618.3 | K78: A second estimate of the same terminal value: what a buyer might pay, at 12 times the final year's EBITDA.
B79: Implied exit multiple from Gordon (x) | D79: =D76/D77 -> 9.4305728 | K79: Our Gordon value works out to about 9.4 times EBITDA — a bit lower than the 12 a buyer might pay. The two methods sit close and point the same way, which is reassuring.
B81: Headline terminal value (Gordon) | D81: =D76 -> 913679.68 | K81: We use the Gordon figure as the main number, to match the Python model. (The CFI template averages the two methods instead.)
B82: Discount factor, year 5 | D82: =1/(1+$D$16)^5 -> 0.55027693 | K82: The terminal value lands at the end of FY31, so we discount it with the year-5 factor.
B83: PV of terminal value | D83: =D81*D82 -> 502776.85 | K83: The terminal value expressed in today's money.
B85: Enterprise Value = PV explicit + PV TV | D85: =D64+D83 -> 711629.13 | K85: Today's value of the whole business: the 5 forecast years plus the terminal value. We compare this with the market's implied business value from Stage 1.
B86: % of EV from terminal value | D86: =D83/D85 -> 0.70651527 | K86: About 70% of the value comes from the terminal value. That is normal for a steady, long-lived company, but it is why the growth and WACC assumptions matter so much.
B89: STAGE 5 — From business value to a verdict on the share | K89: NOTES — plain-language reasons
B90: Enterprise value is the worth of the business itself. To reach what a shareholder's stake is worth, we add the company's spare cash (which shareholders also own, and which we kept out of the yearly cash flows) and subtract its debt (lenders are paid first), then divide by the number of shares. That gives the value of one share, which we compare with the current market price to judge whether the stock looks cheap or expensive. We use TCS's reported cash of ₹50,020 cr here, not the rougher ₹55,000 cr used earlier in Python.
B97: OUR ESTIMATE (from the DCF)
B98: Enterprise Value | D98: =D85 -> 711629.13 | K98: The business value carried down from Stage 4.
B99: Plus: Cash & Investments | D99: =D24 -> 50020 | K99: Shareholders own the company's spare cash on top of the business. We kept this cash out of the yearly cash flows, so we add it back now.
B100: Less: Debt | D100: =D23 -> 11283 | K100: Lenders are paid before shareholders, so we subtract what the company owes.
B101: Equity Value | D101: =D98+D99-D100 -> 750366.13 | K101: What all of TCS's shares are worth together, according to the model.
B102: Shares outstanding (cr) | D102: =D22 -> 361.81 | K102: Number of shares, used to turn total equity into a per-share figure.
B103: Value per share (INR) | D103: =D101/D102 -> 2073.9231 | K103: Our estimate of what one share is worth. Using the Python net-cash figure it would read ₹2,116, almost exactly Python's ₹2,113; the small gap is only the different cash number.
B105: THE MARKET (today)
B106: Current market price (INR) | D106: =D21 -> 2465 | K106: Today's market price. Update it before drawing any conclusion, since it changes daily.
B107: Market cap | D107: =D29 -> 891861.65 | K107: Share price times number of shares.
B109: VERDICT
B110: Upside / (downside) vs our value | D110: =D103/D106-1 -> -0.15865187 | K110: How far the market price is from our estimate. A negative number means the market is higher than our value, so the share looks expensive.
B111: Call | D111: =IF(D103>D106,"UNDERVALUED","OVERVALUED") -> OVERVALUED | K111: Shows 'overvalued' or 'undervalued' on its own, and flips the moment you change the price or any assumption.
B112: Gap per share (INR) | D112: =D103-D106 -> -391.07686 | K112: The difference in rupees between our value and the market price, per share.
B115: STAGE 6 — Working out WACC (the discount rate) | K115: NOTES — plain-language reasons
B116: Until now the 12.7% discount rate was just entered. Here we build it up properly. The cost of equity uses the CAPM formula: the risk-free rate plus beta times the equity risk premium, where beta is the one you measured yourself against the Nifty. The cost of debt is the borrowing rate after the tax saving on interest. We then blend the two in proportion to how much of the company's funding comes from each. TCS is almost entirely equity-funded, so the result is very close to its cost of equity. This WACC feeds back into the discount-rate cell in Stage 1, so the whole model runs on it.
B124: COST OF EQUITY (what shareholders expect)
B125: Risk-free rate (Rf) | D125: 0.0715 | K125: The return on a 10-year Indian government bond, treated as risk-free since the government is assumed to always repay. It is the baseline everyone expects before taking any risk.
B126: Beta (β) | D126: 0.938 | K126: How much TCS's share price moves compared with the whole market. You worked it out yourself from 5 years of weekly TCS returns against the Nifty 50. 0.938 means TCS moves a little less than the market.
B127: Equity risk premium (ERP) | D127: 0.06 | K127: The extra return investors want for holding shares rather than government bonds. About 6% is a reasonable, slightly cautious figure for large Indian companies.
B128: Cost of equity Ke = Rf + β×ERP | D128: =D125+D126*D127 -> 0.12778 | K128: The return TCS's shareholders expect: risk-free rate plus beta times the equity risk premium (the CAPM formula).
B130: COST OF DEBT (what lenders charge)
B131: Pre-tax cost of debt (Kd) | D131: 0.075 | K131: The interest rate TCS would pay to borrow. It is a very safe company, so this is close to the government bond rate.
B132: Tax rate | D132: =D15 -> 0.24 | K132: Linked to the tax rate above. It is used here because interest on debt is tax-deductible, which lowers the real cost of borrowing.
B133: After-tax Kd = Kd×(1−tax) | D133: =D131*(1-D132) -> 0.057 | K133: The borrowing cost after allowing for the tax saving on interest.
B135: MIXING THE TWO (by market value)
B136: Market value of equity (E) | D136: =D29 -> 891861.65 | K136: The market value of TCS's equity (its market cap). We use market value, not the accounting book value, because WACC is about what investors pay today.
B137: Debt (D) | D137: =D23 -> 11283 | K137: The company's debt — just its leases.
B138: Total capital V = E + D | D138: =D136+D137 -> 903144.65 | K138: Equity plus debt: the total money invested in the company.
B139: Equity weight E/V | D139: =D136/D138 -> 0.98750698 | K139: The share of funding that comes from equity — about 99%.
B140: Debt weight D/V | D140: =D137/D138 -> 0.012493015 | K140: The tiny share from debt. Because equity dominates, WACC ends up almost equal to the cost of equity.
B142: WACC = E/V·Ke + D/V·Kd(after-tax) | D142: =D139*D128+D140*D133 -> 0.12689574 | K142: The blended cost of capital: each source's cost weighted by its share. This feeds the discount rate in Stage 1, so changing beta or the risk-free rate flows through the whole model.
B145: STAGE 7 — Sensitivity: value per share across WACC and growth | K145: NOTES — plain-language reasons
B146: A single value of ₹2,074 hides how sensitive the answer is to the assumptions. This grid recalculates the per-share value for every combination of WACC (across the top) and terminal growth (down the side), keeping the forecast cash flows the same. In Excel it is shaded from red to green around the ₹2,465 market price: green means our value is above the market (cheap), red means below (expensive). The honest conclusion is the overall pattern, not any single cell. The steps on the left show how to build it.
B153: How to build this grid yourself | M153: Value ₹/share
B154: 1. Put the WACC values across one row (11.0%–14.5%, in 0.5% steps) and the terminal-growth values down one column (3.0%–6.0%). | M154: g ↓ \ WACC → | N154: 0.11 | O154: =N154+0.005 -> 0.115 | P154: =O154+0.005 -> 0.12 | Q154: =P154+0.005 -> 0.125 | R154: =Q154+0.005 -> 0.13 | S154: =R154+0.005 -> 0.135 | T154: =S154+0.005 -> 0.14 | U154: =T154+0.005 -> 0.145
B155: 2. In each cell, work out the value per share for THAT cell's WACC and growth (not the base case): add each year's cash flow ÷ (1+WACC)^year, add the terminal value ÷ (1+WACC)^5, add net cash, then divide by the number of shares. | M155: 0.03 | N155: =($E$46/(1+N$154)^1+$F$46/(1+N$154)^2+$G$46/(1+N$154)^3+$H$46/(1+N$154)^4+$I$46/(1+N$154)^5+$I$46*(1+$M155)/((N$154-$M155)*(1+N$154)^5)+$D$28)/$D$22 -> 2123.1471 | O155: =($E$46/(1+O$154)^1+$F$46/(1+O$154)^2+$G$46/(1+O$154)^3+$H$46/(1+O$154)^4+$I$46/(1+O$154)^5+$I$46*(1+$M155)/((O$154-$M155)*(1+O$154)^5)+$D$28)/$D$22 -> 2002.6555 | P155: =($E$46/(1+P$154)^1+$F$46/(1+P$154)^2+$G$46/(1+P$154)^3+$H$46/(1+P$154)^4+$I$46/(1+P$154)^5+$I$46*(1+$M155)/((P$154-$M155)*(1+P$154)^5)+$D$28)/$D$22 -> 1895.5834 | Q155: =($E$46/(1+Q$154)^1+$F$46/(1+Q$154)^2+$G$46/(1+Q$154)^3+$H$46/(1+Q$154)^4+$I$46/(1+Q$154)^5+$I$46*(1+$M155)/((Q$154-$M155)*(1+Q$154)^5)+$D$28)/$D$22 -> 1799.8111 | R155: =($E$46/(1+R$154)^1+$F$46/(1+R$154)^2+$G$46/(1+R$154)^3+$H$46/(1+R$154)^4+$I$46/(1+R$154)^5+$I$46*(1+$M155)/((R$154-$M155)*(1+R$154)^5)+$D$28)/$D$22 -> 1713.6431 | S155: =($E$46/(1+S$154)^1+$F$46/(1+S$154)^2+$G$46/(1+S$154)^3+$H$46/(1+S$154)^4+$I$46/(1+S$154)^5+$I$46*(1+$M155)/((S$154-$M155)*(1+S$154)^5)+$D$28)/$D$22 -> 1635.7067 | T155: =($E$46/(1+T$154)^1+$F$46/(1+T$154)^2+$G$46/(1+T$154)^3+$H$46/(1+T$154)^4+$I$46/(1+T$154)^5+$I$46*(1+$M155)/((T$154-$M155)*(1+T$154)^5)+$D$28)/$D$22 -> 1564.8789 | U155: =($E$46/(1+U$154)^1+$F$46/(1+U$154)^2+$G$46/(1+U$154)^3+$H$46/(1+U$154)^4+$I$46/(1+U$154)^5+$I$46*(1+$M155)/((U$154-$M155)*(1+U$154)^5)+$D$28)/$D$22 -> 1500.232
B156: 3. The trick is locking the right part of each reference: lock the WACC to its column heading (N$154) and the growth to its row label ($M155). One formula then copies across the whole grid, each cell picking up its own pair. | M156: =M155+0.005 -> 0.035 | N156: =($E$46/(1+N$154)^1+$F$46/(1+N$154)^2+$G$46/(1+N$154)^3+$H$46/(1+N$154)^4+$I$46/(1+N$154)^5+$I$46*(1+$M156)/((N$154-$M156)*(1+N$154)^5)+$D$28)/$D$22 -> 2224.6675 | O156: =($E$46/(1+O$154)^1+$F$46/(1+O$154)^2+$G$46/(1+O$154)^3+$H$46/(1+O$154)^4+$I$46/(1+O$154)^5+$I$46*(1+$M156)/((O$154-$M156)*(1+O$154)^5)+$D$28)/$D$22 -> 2090.6363 | P156: =($E$46/(1+P$154)^1+$F$46/(1+P$154)^2+$G$46/(1+P$154)^3+$H$46/(1+P$154)^4+$I$46/(1+P$154)^5+$I$46*(1+$M156)/((P$154-$M156)*(1+P$154)^5)+$D$28)/$D$22 -> 1972.4013 | Q156: =($E$46/(1+Q$154)^1+$F$46/(1+Q$154)^2+$G$46/(1+Q$154)^3+$H$46/(1+Q$154)^4+$I$46/(1+Q$154)^5+$I$46*(1+$M156)/((Q$154-$M156)*(1+Q$154)^5)+$D$28)/$D$22 -> 1867.3292 | R156: =($E$46/(1+R$154)^1+$F$46/(1+R$154)^2+$G$46/(1+R$154)^3+$H$46/(1+R$154)^4+$I$46/(1+R$154)^5+$I$46*(1+$M156)/((R$154-$M156)*(1+R$154)^5)+$D$28)/$D$22 -> 1773.341 | S156: =($E$46/(1+S$154)^1+$F$46/(1+S$154)^2+$G$46/(1+S$154)^3+$H$46/(1+S$154)^4+$I$46/(1+S$154)^5+$I$46*(1+$M156)/((S$154-$M156)*(1+S$154)^5)+$D$28)/$D$22 -> 1688.7736 | T156: =($E$46/(1+T$154)^1+$F$46/(1+T$154)^2+$G$46/(1+T$154)^3+$H$46/(1+T$154)^4+$I$46/(1+T$154)^5+$I$46*(1+$M156)/((T$154-$M156)*(1+T$154)^5)+$D$28)/$D$22 -> 1612.2807 | U156: =($E$46/(1+U$154)^1+$F$46/(1+U$154)^2+$G$46/(1+U$154)^3+$H$46/(1+U$154)^4+$I$46/(1+U$154)^5+$I$46*(1+$M156)/((U$154-$M156)*(1+U$154)^5)+$D$28)/$D$22 -> 1542.7609
B157: 4. Select the grid, then Home → Conditional Formatting → Colour Scales, and set the middle point to the market price so green = cheaper than our value and red = dearer. | M157: =M156+0.005 -> 0.04 | N157: =($E$46/(1+N$154)^1+$F$46/(1+N$154)^2+$G$46/(1+N$154)^3+$H$46/(1+N$154)^4+$I$46/(1+N$154)^5+$I$46*(1+$M157)/((N$154-$M157)*(1+N$154)^5)+$D$28)/$D$22 -> 2340.6908 | O157: =($E$46/(1+O$154)^1+$F$46/(1+O$154)^2+$G$46/(1+O$154)^3+$H$46/(1+O$154)^4+$I$46/(1+O$154)^5+$I$46*(1+$M157)/((O$154-$M157)*(1+O$154)^5)+$D$28)/$D$22 -> 2190.3479 | P157: =($E$46/(1+P$154)^1+$F$46/(1+P$154)^2+$G$46/(1+P$154)^3+$H$46/(1+P$154)^4+$I$46/(1+P$154)^5+$I$46*(1+$M157)/((P$154-$M157)*(1+P$154)^5)+$D$28)/$D$22 -> 2058.8216 | Q157: =($E$46/(1+Q$154)^1+$F$46/(1+Q$154)^2+$G$46/(1+Q$154)^3+$H$46/(1+Q$154)^4+$I$46/(1+Q$154)^5+$I$46*(1+$M157)/((Q$154-$M157)*(1+Q$154)^5)+$D$28)/$D$22 -> 1942.7906 | R157: =($E$46/(1+R$154)^1+$F$46/(1+R$154)^2+$G$46/(1+R$154)^3+$H$46/(1+R$154)^4+$I$46/(1+R$154)^5+$I$46*(1+$M157)/((R$154-$M157)*(1+R$154)^5)+$D$28)/$D$22 -> 1839.672 | S157: =($E$46/(1+S$154)^1+$F$46/(1+S$154)^2+$G$46/(1+S$154)^3+$H$46/(1+S$154)^4+$I$46/(1+S$154)^5+$I$46*(1+$M157)/((S$154-$M157)*(1+S$154)^5)+$D$28)/$D$22 -> 1747.4265 | T157: =($E$46/(1+T$154)^1+$F$46/(1+T$154)^2+$G$46/(1+T$154)^3+$H$46/(1+T$154)^4+$I$46/(1+T$154)^5+$I$46*(1+$M157)/((T$154-$M157)*(1+T$154)^5)+$D$28)/$D$22 -> 1664.4228 | U157: =($E$46/(1+U$154)^1+$F$46/(1+U$154)^2+$G$46/(1+U$154)^3+$H$46/(1+U$154)^4+$I$46/(1+U$154)^5+$I$46*(1+$M157)/((U$154-$M157)*(1+U$154)^5)+$D$28)/$D$22 -> 1589.3402
B158: 5. Change any forecast input and the whole grid updates, because every cell points back to the same cash-flow row. | M158: =M157+0.005 -> 0.045 | N158: =($E$46/(1+N$154)^1+$F$46/(1+N$154)^2+$G$46/(1+N$154)^3+$H$46/(1+N$154)^4+$I$46/(1+N$154)^5+$I$46*(1+$M158)/((N$154-$M158)*(1+N$154)^5)+$D$28)/$D$22 -> 2474.5638 | O158: =($E$46/(1+O$154)^1+$F$46/(1+O$154)^2+$G$46/(1+O$154)^3+$H$46/(1+O$154)^4+$I$46/(1+O$154)^5+$I$46*(1+$M158)/((O$154-$M158)*(1+O$154)^5)+$D$28)/$D$22 -> 2304.3041 | P158: =($E$46/(1+P$154)^1+$F$46/(1+P$154)^2+$G$46/(1+P$154)^3+$H$46/(1+P$154)^4+$I$46/(1+P$154)^5+$I$46*(1+$M158)/((P$154-$M158)*(1+P$154)^5)+$D$28)/$D$22 -> 2156.7645 | Q158: =($E$46/(1+Q$154)^1+$F$46/(1+Q$154)^2+$G$46/(1+Q$154)^3+$H$46/(1+Q$154)^4+$I$46/(1+Q$154)^5+$I$46*(1+$M158)/((Q$154-$M158)*(1+Q$154)^5)+$D$28)/$D$22 -> 2027.6847 | R158: =($E$46/(1+R$154)^1+$F$46/(1+R$154)^2+$G$46/(1+R$154)^3+$H$46/(1+R$154)^4+$I$46/(1+R$154)^5+$I$46*(1+$M158)/((R$154-$M158)*(1+R$154)^5)+$D$28)/$D$22 -> 1913.8066 | S158: =($E$46/(1+S$154)^1+$F$46/(1+S$154)^2+$G$46/(1+S$154)^3+$H$46/(1+S$154)^4+$I$46/(1+S$154)^5+$I$46*(1+$M158)/((S$154-$M158)*(1+S$154)^5)+$D$28)/$D$22 -> 1812.5963 | T158: =($E$46/(1+T$154)^1+$F$46/(1+T$154)^2+$G$46/(1+T$154)^3+$H$46/(1+T$154)^4+$I$46/(1+T$154)^5+$I$46*(1+$M158)/((T$154-$M158)*(1+T$154)^5)+$D$28)/$D$22 -> 1722.0534 | U158: =($E$46/(1+U$154)^1+$F$46/(1+U$154)^2+$G$46/(1+U$154)^3+$H$46/(1+U$154)^4+$I$46/(1+U$154)^5+$I$46*(1+$M158)/((U$154-$M158)*(1+U$154)^5)+$D$28)/$D$22 -> 1640.5773
M159: =M158+0.005 -> 0.05 | N159: =($E$46/(1+N$154)^1+$F$46/(1+N$154)^2+$G$46/(1+N$154)^3+$H$46/(1+N$154)^4+$I$46/(1+N$154)^5+$I$46*(1+$M159)/((N$154-$M159)*(1+N$154)^5)+$D$28)/$D$22 -> 2630.749 | O159: =($E$46/(1+O$154)^1+$F$46/(1+O$154)^2+$G$46/(1+O$154)^3+$H$46/(1+O$154)^4+$I$46/(1+O$154)^5+$I$46*(1+$M159)/((O$154-$M159)*(1+O$154)^5)+$D$28)/$D$22 -> 2435.7919 | P159: =($E$46/(1+P$154)^1+$F$46/(1+P$154)^2+$G$46/(1+P$154)^3+$H$46/(1+P$154)^4+$I$46/(1+P$154)^5+$I$46*(1+$M159)/((P$154-$M159)*(1+P$154)^5)+$D$28)/$D$22 -> 2268.6993 | Q159: =($E$46/(1+Q$154)^1+$F$46/(1+Q$154)^2+$G$46/(1+Q$154)^3+$H$46/(1+Q$154)^4+$I$46/(1+Q$154)^5+$I$46*(1+$M159)/((Q$154-$M159)*(1+Q$154)^5)+$D$28)/$D$22 -> 2123.898 | R159: =($E$46/(1+R$154)^1+$F$46/(1+R$154)^2+$G$46/(1+R$154)^3+$H$46/(1+R$154)^4+$I$46/(1+R$154)^5+$I$46*(1+$M159)/((R$154-$M159)*(1+R$154)^5)+$D$28)/$D$22 -> 1997.2081 | S159: =($E$46/(1+S$154)^1+$F$46/(1+S$154)^2+$G$46/(1+S$154)^3+$H$46/(1+S$154)^4+$I$46/(1+S$154)^5+$I$46*(1+$M159)/((S$154-$M159)*(1+S$154)^5)+$D$28)/$D$22 -> 1885.4333 | T159: =($E$46/(1+T$154)^1+$F$46/(1+T$154)^2+$G$46/(1+T$154)^3+$H$46/(1+T$154)^4+$I$46/(1+T$154)^5+$I$46*(1+$M159)/((T$154-$M159)*(1+T$154)^5)+$D$28)/$D$22 -> 1786.0874 | U159: =($E$46/(1+U$154)^1+$F$46/(1+U$154)^2+$G$46/(1+U$154)^3+$H$46/(1+U$154)^4+$I$46/(1+U$154)^5+$I$46*(1+$M159)/((U$154-$M159)*(1+U$154)^5)+$D$28)/$D$22 -> 1697.2079
M160: =M159+0.005 -> 0.055 | N160: =($E$46/(1+N$154)^1+$F$46/(1+N$154)^2+$G$46/(1+N$154)^3+$H$46/(1+N$154)^4+$I$46/(1+N$154)^5+$I$46*(1+$M160)/((N$154-$M160)*(1+N$154)^5)+$D$28)/$D$22 -> 2815.3315 | O160: =($E$46/(1+O$154)^1+$F$46/(1+O$154)^2+$G$46/(1+O$154)^3+$H$46/(1+O$154)^4+$I$46/(1+O$154)^5+$I$46*(1+$M160)/((O$154-$M160)*(1+O$154)^5)+$D$28)/$D$22 -> 2589.1943 | P160: =($E$46/(1+P$154)^1+$F$46/(1+P$154)^2+$G$46/(1+P$154)^3+$H$46/(1+P$154)^4+$I$46/(1+P$154)^5+$I$46*(1+$M160)/((P$154-$M160)*(1+P$154)^5)+$D$28)/$D$22 -> 2397.8548 | Q160: =($E$46/(1+Q$154)^1+$F$46/(1+Q$154)^2+$G$46/(1+Q$154)^3+$H$46/(1+Q$154)^4+$I$46/(1+Q$154)^5+$I$46*(1+$M160)/((Q$154-$M160)*(1+Q$154)^5)+$D$28)/$D$22 -> 2233.856 | R160: =($E$46/(1+R$154)^1+$F$46/(1+R$154)^2+$G$46/(1+R$154)^3+$H$46/(1+R$154)^4+$I$46/(1+R$154)^5+$I$46*(1+$M160)/((R$154-$M160)*(1+R$154)^5)+$D$28)/$D$22 -> 2091.7298 | S160: =($E$46/(1+S$154)^1+$F$46/(1+S$154)^2+$G$46/(1+S$154)^3+$H$46/(1+S$154)^4+$I$46/(1+S$154)^5+$I$46*(1+$M160)/((S$154-$M160)*(1+S$154)^5)+$D$28)/$D$22 -> 1967.3748 | T160: =($E$46/(1+T$154)^1+$F$46/(1+T$154)^2+$G$46/(1+T$154)^3+$H$46/(1+T$154)^4+$I$46/(1+T$154)^5+$I$46*(1+$M160)/((T$154-$M160)*(1+T$154)^5)+$D$28)/$D$22 -> 1857.6549 | U160: =($E$46/(1+U$154)^1+$F$46/(1+U$154)^2+$G$46/(1+U$154)^3+$H$46/(1+U$154)^4+$I$46/(1+U$154)^5+$I$46*(1+$M160)/((U$154-$M160)*(1+U$154)^5)+$D$28)/$D$22 -> 1760.1307
M161: =M160+0.005 -> 0.06 | N161: =($E$46/(1+N$154)^1+$F$46/(1+N$154)^2+$G$46/(1+N$154)^3+$H$46/(1+N$154)^4+$I$46/(1+N$154)^5+$I$46*(1+$M161)/((N$154-$M161)*(1+N$154)^5)+$D$28)/$D$22 -> 3036.8305 | O161: =($E$46/(1+O$154)^1+$F$46/(1+O$154)^2+$G$46/(1+O$154)^3+$H$46/(1+O$154)^4+$I$46/(1+O$154)^5+$I$46*(1+$M161)/((O$154-$M161)*(1+O$154)^5)+$D$28)/$D$22 -> 2770.4882 | P161: =($E$46/(1+P$154)^1+$F$46/(1+P$154)^2+$G$46/(1+P$154)^3+$H$46/(1+P$154)^4+$I$46/(1+P$154)^5+$I$46*(1+$M161)/((P$154-$M161)*(1+P$154)^5)+$D$28)/$D$22 -> 2548.5362 | Q161: =($E$46/(1+Q$154)^1+$F$46/(1+Q$154)^2+$G$46/(1+Q$154)^3+$H$46/(1+Q$154)^4+$I$46/(1+Q$154)^5+$I$46*(1+$M161)/((Q$154-$M161)*(1+Q$154)^5)+$D$28)/$D$22 -> 2360.7307 | R161: =($E$46/(1+R$154)^1+$F$46/(1+R$154)^2+$G$46/(1+R$154)^3+$H$46/(1+R$154)^4+$I$46/(1+R$154)^5+$I$46*(1+$M161)/((R$154-$M161)*(1+R$154)^5)+$D$28)/$D$22 -> 2199.7545 | S161: =($E$46/(1+S$154)^1+$F$46/(1+S$154)^2+$G$46/(1+S$154)^3+$H$46/(1+S$154)^4+$I$46/(1+S$154)^5+$I$46*(1+$M161)/((S$154-$M161)*(1+S$154)^5)+$D$28)/$D$22 -> 2060.2419 | T161: =($E$46/(1+T$154)^1+$F$46/(1+T$154)^2+$G$46/(1+T$154)^3+$H$46/(1+T$154)^4+$I$46/(1+T$154)^5+$I$46*(1+$M161)/((T$154-$M161)*(1+T$154)^5)+$D$28)/$D$22 -> 1938.1683 | U161: =($E$46/(1+U$154)^1+$F$46/(1+U$154)^2+$G$46/(1+U$154)^3+$H$46/(1+U$154)^4+$I$46/(1+U$154)^5+$I$46*(1+$M161)/((U$154-$M161)*(1+U$154)^5)+$D$28)/$D$22 -> 1830.4563
M163: Base ≈ WACC 12.7%, g 5% → ₹2,074 · Market ₹2,465 = the colour midpoint

Sheet Summary
B2: TCS — DCF Valuation Summary
B3: All figures INR crore unless per-share · Consolidated · see 'DCF Model' sheet for workings
B5: Key assumptions
B6: WACC | D6: ='DCF Model'!D16 -> 0.12689574
B7: Terminal growth (g) | D7: ='DCF Model'!D17 -> 0.05
B8: Explicit growth | D8: ='DCF Model'!D18 -> 0.06
B9: Tax rate | D9: ='DCF Model'!D15 -> 0.24
B10: Shares outstanding (cr) | D10: ='DCF Model'!D22 -> 361.81
B11: Current price (INR) | D11: ='DCF Model'!D21 -> 2465
B13: Valuation build
B14: PV of explicit FCFs (FY27–31) | D14: ='DCF Model'!D64 -> 208852.28
B15: PV of terminal value | D15: ='DCF Model'!D83 -> 502776.85
B16: Enterprise Value | D16: ='DCF Model'!D85 -> 711629.13
B17: Plus: Cash & Investments | D17: ='DCF Model'!D24 -> 50020
B18: Less: Debt | D18: ='DCF Model'!D23 -> 11283
B19: Equity Value | D19: ='DCF Model'!D101 -> 750366.13
B21: Result
B22: Value / share (INR) | D22: ='DCF Model'!D103 -> 2073.9231
B23: Market price / share (INR) | D23: ='DCF Model'!D21 -> 2465
B24: Upside / (downside) | D24: ='DCF Model'!D110 -> -0.15865187
B25: Call | D25: ='DCF Model'!D111 -> OVERVALUED
B27: Thesis: at the base case (WACC about 12.7%, growth 5%) TCS looks modestly overvalued. It only looks cheap at a WACC below 11.5% or growth near 6%. These figures match the Python model to the rupee through enterprise value.
